.VERSION
AUTHORS.rst
CONTRIBUTING.rst
HISTORY.rst
LICENSE
MANIFEST.in
Pipfile
Pipfile.lock
README.rst
USAGE.rst
dev-requirements.txt
requirements.txt
setup.cfg
setup.py
azureenergylabelerlib/.VERSION
azureenergylabelerlib/AUTHORS.rst
azureenergylabelerlib/CONTRIBUTING.rst
azureenergylabelerlib/HISTORY.rst
azureenergylabelerlib/LICENSE
azureenergylabelerlib/Pipfile
azureenergylabelerlib/Pipfile.lock
azureenergylabelerlib/README.rst
azureenergylabelerlib/USAGE.rst
azureenergylabelerlib/__init__.py
azureenergylabelerlib/_version.py
azureenergylabelerlib/azureenergylabelerlib.py
azureenergylabelerlib/azureenergylabelerlibexceptions.py
azureenergylabelerlib/configuration.py
azureenergylabelerlib/datamodels.py
azureenergylabelerlib/dev-requirements.txt
azureenergylabelerlib/entities.py
azureenergylabelerlib/labels.py
azureenergylabelerlib/requirements.txt
azureenergylabelerlib/schemas.py
azureenergylabelerlib/validations.py
azureenergylabelerlib.egg-info/PKG-INFO
azureenergylabelerlib.egg-info/SOURCES.txt
azureenergylabelerlib.egg-info/dependency_links.txt
azureenergylabelerlib.egg-info/not-zip-safe
azureenergylabelerlib.egg-info/requires.txt
azureenergylabelerlib.egg-info/top_level.txt
docs/Makefile
docs/authors.rst
docs/conf.py
docs/contributing.rst
docs/history.rst
docs/index.rst
docs/installation.rst
docs/readme.rst
docs/usage.rst
tests/test_azureenergylabelerlib.py