Metadata-Version: 2.1
Name: azureenergylabelerlib
Version: 3.3.1
Summary: A python library that generates energy labels based on findings in Azure subscriptions
Home-page: https://github.com/schubergphilis/azureenergylabelerlib
Author: Sayantan Khanra
Author-email: skhanra@schubergphilis.com
License: MIT
Keywords: azureenergylabelerlib
Classifier: Development Status :: 1 - Planning
Classifier: Intended Audience :: Developers
Classifier: License :: OSI Approved :: MIT License
Classifier: Natural Language :: English
Classifier: Programming Language :: Python :: 3.7
License-File: LICENSE
License-File: AUTHORS.rst
Requires-Dist: azure-mgmt-security>=1.0.0
Requires-Dist: azure-identity>=1.14.0; python_version >= "3.7"
Requires-Dist: azure-cli-core>=2.53.0; python_full_version >= "3.8.0"
Requires-Dist: azure-mgmt-resourcegraph>=8.0.0
Requires-Dist: azure-mgmt-resource>=21.2.1; python_version >= "3.7"
Requires-Dist: azure-storage-blob>=12.18.2; python_version >= "3.7"
Requires-Dist: schema>=0.7.5
Requires-Dist: cachetools>=5.3.1; python_version >= "3.7"
Requires-Dist: opnieuw>=1.2.1; python_version >= "3.7"
